utilities/__init__.py
utilities/data_processing.py
utilities/job_management.py
topaz_data_reduction-0.1.2.dist-info/METADATA
topaz_data_reduction-0.1.2.dist-info/WHEEL
topaz_data_reduction-0.1.2.dist-info/top_level.txt
topaz_data_reduction-0.1.2.dist-info/RECORD
